redmx/VERSION
redmx/__init__.py
redmx-0.2.2.dist-info/LICENSE
redmx-0.2.2.dist-info/METADATA
redmx-0.2.2.dist-info/WHEEL
redmx-0.2.2.dist-info/top_level.txt
redmx-0.2.2.dist-info/RECORD
