Metadata-Version: 2.1
Name: redmx
Version: 0.2.2
Summary: Rate, Errors and Duration Metrics.
Home-page: https://github.com/locp/redmx
Author: League of Crafty Programmers Ltd.
Author-email: info@locp.co.uk
License: UNKNOWN
Project-URL: Bug Tracker, https://github.com/locp/redmx/issues
Keywords: metrics
Platform: UNKNOWN
Classifier: Programming Language :: Python :: 3
Classifier: License :: OSI Approved :: BSD License
Classifier: Operating System :: OS Independent
Requires-Python: >=3.8
License-File: LICENSE
